autoclipper/__init__.py
autoclipper/autoclipper.py
gradientnorm_autoclipper-1.0.0.dist-info/LICENSE
gradientnorm_autoclipper-1.0.0.dist-info/METADATA
gradientnorm_autoclipper-1.0.0.dist-info/WHEEL
gradientnorm_autoclipper-1.0.0.dist-info/top_level.txt
gradientnorm_autoclipper-1.0.0.dist-info/RECORD
