Metadata-Version: 2.1
Name: gradientnorm-autoclipper
Version: 1.0.0
Summary: Clip gradient norm automatically
Author-email: Michał Dyczko <michal@dyczko.dev>
License: MIT License
Project-URL: Homepage, https://github.com/michaldyczko/gradientnorm-autoclipper
Keywords: pytorch,gradient clipping,automl
Requires-Python: >=3.8
License-File: LICENSE
Requires-Dist: torch >=2.2.1
Requires-Dist: pytorch-optimizer >=3.0.0
